sourmash_plugin_commonhash.py
sourmash_plugin_commonhash-0.4.dist-info/LICENSE
sourmash_plugin_commonhash-0.4.dist-info/METADATA
sourmash_plugin_commonhash-0.4.dist-info/WHEEL
sourmash_plugin_commonhash-0.4.dist-info/entry_points.txt
sourmash_plugin_commonhash-0.4.dist-info/top_level.txt
sourmash_plugin_commonhash-0.4.dist-info/RECORD
