Metadata-Version: 2.1
Name: sourmash-plugin-commonhash
Version: 0.4
Summary: sourmash plugin to calculate common hashes across multiple sketches.
Requires-Python: >=3.8
License-File: LICENSE
Requires-Dist: sourmash <5,>=4.8.0
